krxfetch/__init__.py
krxfetch/_chrome.py
krxfetch/_holiday.py
krxfetch/calendar.py
krxfetch/fetch.py
krxfetch-2026.2.dist-info/licenses/LICENSE
krxfetch-2026.2.dist-info/METADATA
krxfetch-2026.2.dist-info/WHEEL
krxfetch-2026.2.dist-info/top_level.txt
krxfetch-2026.2.dist-info/RECORD
