Metadata-Version: 2.4
Name: krxfetch
Version: 2026.2
Summary: KRXFetch is a core library for scraping financial data from the KRX(Korea Exchange) Market Data System.
Author-email: Gunhoon Lee <gunhoon@gmail.com>
License: MIT License
Requires-Python: >=3.8
License-File: LICENSE
Requires-Dist: requests
Dynamic: license-file
